hydrax/__init__.py
hydrax/_trackedbuffer.cpython-312-x86_64-linux-gnu.so
hydrax/_trackedbuffer.pyi
hydrax/image.py
hydrax/pandas.py
hydrax/tqdm.py
hydrax-0.2.2.dist-info/LICENSE
hydrax-0.2.2.dist-info/METADATA
hydrax-0.2.2.dist-info/WHEEL
hydrax-0.2.2.dist-info/top_level.txt
hydrax-0.2.2.dist-info/RECORD
