Metadata-Version: 2.1
Name: hydrax
Version: 0.2.2
Summary: A zero-copy multiprocess dataloader for JAX.
Author-email: RedHotTensors <159090586+redhottensors@users.noreply.github.com>
License: Mozilla Public License Version 2.0
Project-URL: Homepage, https://github.com/redhottensors/hydrax
Project-URL: Documentation, https://redhottensors.github.io/hydrax/_autosummary/hydrax.html
Keywords: JAX,dataloader
Classifier: Development Status :: 3 - Alpha
Classifier: Intended Audience :: Science/Research
Classifier: License :: OSI Approved :: Mozilla Public License 2.0 (MPL 2.0)
Classifier: Natural Language :: English
Classifier: Operating System :: OS Independent
Classifier: Programming Language :: C
Classifier: Programming Language :: Python :: 3
Classifier: Programming Language :: Python :: Implementation :: CPython
Classifier: Topic :: Scientific/Engineering :: Artificial Intelligence
Classifier: Topic :: Scientific/Engineering :: Image Processing
Classifier: Typing :: Typed
Requires-Python: >=3.10
License-File: LICENSE
Requires-Dist: numpy
Requires-Dist: jax
Provides-Extra: all
Requires-Dist: Pillow ; extra == 'all'
Requires-Dist: pandas ; extra == 'all'
Requires-Dist: tqdm ; extra == 'all'
Provides-Extra: image
Requires-Dist: Pillow ; extra == 'image'
Provides-Extra: pandas
Requires-Dist: pandas ; extra == 'pandas'
Provides-Extra: tqdm
Requires-Dist: tqdm ; extra == 'tqdm'
